turbESN/__init__.py
turbESN/__version__.py
turbESN/_modes.py
turbESN/_version.py
turbESN/core.py
turbESN/cross_validation.py
turbESN/hyperparameters.json
turbESN/logging_config.json
turbESN/study.py
turbESN/util.py
turbESN/info/__init__.py
turbESN/info/hyperparameters.json
turbESN-0.0.1.9.5.0.dist-info/LICENSE
turbESN-0.0.1.9.5.0.dist-info/METADATA
turbESN-0.0.1.9.5.0.dist-info/WHEEL
turbESN-0.0.1.9.5.0.dist-info/top_level.txt
turbESN-0.0.1.9.5.0.dist-info/RECORD
