Metadata-Version: 2.1
Name: turbESN
Version: 0.0.1.9.5.0
Summary: An echo state network implementation.
Home-page: UNKNOWN
Author: flohey (Florian Heyder)
Author-email: <florian.heyder@protonmail.com>
License: UNKNOWN
Keywords: python,ESN,reservoir computing,echo state network,recurrent neural network
Platform: UNKNOWN
Classifier: Development Status :: 1 - Planning
Classifier: Intended Audience :: Developers
Classifier: Programming Language :: Python :: 3
Classifier: Operating System :: Unix
Classifier: Operating System :: MacOS :: MacOS X
Classifier: Operating System :: Microsoft :: Windows
Requires-Python: >=3.7.0
License-File: LICENSE
Requires-Dist: numpy
Requires-Dist: multiprocess
Requires-Dist: h5py
Requires-Dist: scipy
